cg_dt_utils/__init__.py
cg_dt_utils/py.typed
cg_maybe/__init__.py
cg_maybe/_just.py
cg_maybe/_maybe.py
cg_maybe/_nothing.py
cg_maybe/_type_helpers.py
cg_maybe/cg_maybe_plugin.py
cg_maybe/py.typed
cg_maybe/utils.py
cg_request_args/__init__.py
cg_request_args/_any_value.py
cg_request_args/_base.py
cg_request_args/_convert.py
cg_request_args/_enum.py
cg_request_args/_form.py
cg_request_args/_lazy.py
cg_request_args/_list.py
cg_request_args/_literal.py
cg_request_args/_mapping.py
cg_request_args/_multipart.py
cg_request_args/_nullable.py
cg_request_args/_parse_utils.py
cg_request_args/_query.py
cg_request_args/_rich_value.py
cg_request_args/_set.py
cg_request_args/_swagger_utils.py
cg_request_args/_swaggerize.py
cg_request_args/_utils.py
cg_request_args/exceptions.py
cg_request_args/py.typed
cg_request_args/request_args_plugin.py
codegrade/__init__.py
codegrade/client.py
codegrade/errors.py
codegrade/paginated.py
codegrade/parsers.py
codegrade/py.typed
codegrade/utils.py
codegrade/_api/__init__.py
codegrade/_api/about.py
codegrade/_api/access_plan.py
codegrade/_api/assignment.py
codegrade/_api/auto_test.py
codegrade/_api/comment.py
codegrade/_api/course.py
codegrade/_api/course_price.py
codegrade/_api/file.py
codegrade/_api/git_provider.py
codegrade/_api/group.py
codegrade/_api/group_set.py
codegrade/_api/login_link.py
codegrade/_api/lti.py
codegrade/_api/notification.py
codegrade/_api/oauth_provider.py
codegrade/_api/oauth_token.py
codegrade/_api/permission.py
codegrade/_api/plagiarism.py
codegrade/_api/role.py
codegrade/_api/saml.py
codegrade/_api/section.py
codegrade/_api/site_settings.py
codegrade/_api/snippet.py
codegrade/_api/sso_provider.py
codegrade/_api/submission.py
codegrade/_api/task_result.py
codegrade/_api/tenant.py
codegrade/_api/transaction.py
codegrade/_api/user.py
codegrade/_api/user_setting.py
codegrade/_api/webhook.py
codegrade/models/__init__.py
codegrade/models/_submission_rubric_item_data_parser.py
codegrade/models/about.py
codegrade-17.0.27.dist-info/METADATA
codegrade-17.0.27.dist-info/WHEEL
codegrade-17.0.27.dist-info/RECORD
