Metadata-Version: 2.4
Name: codegrade
Version: 17.0.27
Summary: A client library for accessing CodeGrade
Project-URL: Documentation, https://python.api.codegrade.com
License-Expression: AGPL-3.0-only OR BSD-3-Clause-Clear
Requires-Python: <4.0,>=3.8.0
Requires-Dist: httpx<1.0.0,>=0.19.0
Requires-Dist: python-dateutil<3,>=2.8.1
Requires-Dist: structlog>=20.1.0
Requires-Dist: typing-extensions<5,>=4.13.2
Requires-Dist: validate-email~=1.3
